vidata/__init__.py
vidata/config_manager.py
vidata/playground.py
vidata/registry.py
vidata/analysis/__init__.py
vidata/analysis/base_analyzer.py
vidata/analysis/image_analyzer.py
vidata/analysis/label_analyzer.py
vidata/analysis/utils.py
vidata/analysis/viz_utils.py
vidata/cli/__init__.py
vidata/cli/analyze.py
vidata/cli/template.py
vidata/file_manager/__init__.py
vidata/file_manager/file_manager.py
vidata/io/__init__.py
vidata/io/blosc2_io.py
vidata/io/cv2_io.py
vidata/io/image_io.py
vidata/io/json_io.py
vidata/io/nib_io.py
vidata/io/nrrd_io.py
vidata/io/numpy_io.py
vidata/io/pickle_io.py
vidata/io/sitk_io.py
vidata/io/tif_io.py
vidata/io/txt_io.py
vidata/io/yaml_io.py
vidata/loaders/__init__.py
vidata/loaders/base_loader.py
vidata/loaders/image_loader.py
vidata/loaders/multilabel_loader.py
vidata/loaders/semseg_loader.py
vidata/playground/desy.py
vidata/task_manager/__init__.py
vidata/task_manager/image_manager.py
vidata/task_manager/multilabel_segmentation_manager.py
vidata/task_manager/semantic_segmentation_manager.py
vidata/task_manager/task_manager.py
vidata/utils/__init__.py
vidata/utils/affine.py
vidata/utils/color.py
vidata/utils/metric.py
vidata/utils/multiprocess.py
vidata/utils/path_utils.py
vidata/writers/__init__.py
vidata/writers/base_writer.py
vidata/writers/image_writer.py
vidata/writers/multilabel_writer.py
vidata/writers/semseg_writer.py
vidata-1.0.5.dist-info/licenses/LICENSE
vidata-1.0.5.dist-info/METADATA
vidata-1.0.5.dist-info/WHEEL
vidata-1.0.5.dist-info/entry_points.txt
vidata-1.0.5.dist-info/top_level.txt
vidata-1.0.5.dist-info/RECORD
