Metadata-Version: 2.4
Name: vidata
Version: 1.0.5
Summary: A unified Python toolkit for managing, processing, and analyzing vision datasets, from raw data to task specific analytics.
Author: Lars Krämer
Author-email: lars.kraemer@dkfz-heidelberg.de
License: 
Project-URL: Documentation, https://github.com/MIC-DKFZ/vidata#README.md
Project-URL: Source Code, https://github.com/MIC-DKFZ/vidata
Classifier: Development Status :: 2 - Pre-Alpha
Classifier: Intended Audience :: Developers
Classifier: License :: OSI Approved :: Apache Software License
Classifier: Operating System :: OS Independent
Classifier: Programming Language :: Python
Classifier: Programming Language :: Python :: 3
Classifier: Programming Language :: Python :: 3 :: Only
Classifier: Programming Language :: Python :: 3.10
Classifier: Programming Language :: Python :: 3.11
Classifier: Programming Language :: Python :: 3.12
Classifier: Programming Language :: Python :: 3.13
Classifier: Topic :: Scientific/Engineering :: Image Processing
Requires-Python: >=3.10
License-File: LICENSE
Requires-Dist: numpy
Requires-Dist: blosc2
Requires-Dist: SimpleITK
Requires-Dist: nibabel
Requires-Dist: imageio
Requires-Dist: tifffile
Requires-Dist: plotly
Requires-Dist: kaleido
Requires-Dist: natsort
Requires-Dist: omegaconf
Requires-Dist: pyyaml
Requires-Dist: seaborn
Requires-Dist: scikit-learn
Requires-Dist: opencv-python-headless
Requires-Dist: pynrrd
Provides-Extra: testing
Requires-Dist: tox; extra == "testing"
Requires-Dist: pytest; extra == "testing"
Requires-Dist: pytest-cov; extra == "testing"
Dynamic: license-file
